enablebanking_cli/__init__.py
enablebanking_cli/__main__.py
enablebanking_cli/__version__.py
enablebanking_cli/cli.py
enablebanking_cli/cp_client.py
enablebanking_cli/cp_store.py
enablebanking_cli/commands/__init__.py
enablebanking_cli/commands/app.py
enablebanking_cli/commands/aspsp.py
enablebanking_cli/commands/auth.py
enablebanking_cli/commands/base.py
enablebanking_cli-0.2.2.dist-info/LICENSE
enablebanking_cli-0.2.2.dist-info/METADATA
enablebanking_cli-0.2.2.dist-info/WHEEL
enablebanking_cli-0.2.2.dist-info/entry_points.txt
enablebanking_cli-0.2.2.dist-info/top_level.txt
enablebanking_cli-0.2.2.dist-info/RECORD
