Metadata-Version: 2.1
Name: enablebanking_cli
Version: 0.2.2
Summary: Enable Banking Command Line Interface
Home-page: https://github.com/enablebanking/enablebanking-cli
Author: Enable Banking team
Author-email: support.api@enablebanking.com
License: Apache License 2.0
Project-URL: Source, https://github.com/enablebanking/enablebanking-cli
Project-URL: Changelog, https://github.com/enablebanking/enablebanking-cli/blob/main/CHANGELOG.md
Classifier: Development Status :: 2 - Pre-Alpha
Classifier: Environment :: Console
Classifier: Intended Audience :: Developers
Classifier: License :: OSI Approved :: Apache Software License
Classifier: Operating System :: OS Independent
Classifier: Programming Language :: Python
Classifier: Programming Language :: Python :: 3
Classifier: Programming Language :: Python :: 3.8
Classifier: Programming Language :: Python :: 3 :: Only
Classifier: Programming Language :: Python :: Implementation :: CPython
Classifier: Programming Language :: Python :: Implementation :: PyPy
Requires-Python: >=3.8.0
License-File: LICENSE
